pixtreme_legacy/__init__.py
pixtreme_legacy/color/__init__.py
pixtreme_legacy/color/uyvy422.py
pixtreme_legacy/color/uyvy422_ndi.py
pixtreme_legacy/color/yuv420.py
pixtreme_legacy/color/yuv422p10le.py
pixtreme_legacy/color/lut/__init__.py
pixtreme_legacy/color/lut/apply_lut.py
pixtreme_legacy-0.8.6.dist-info/METADATA
pixtreme_legacy-0.8.6.dist-info/WHEEL
pixtreme_legacy-0.8.6.dist-info/licenses/LICENSE
pixtreme_legacy-0.8.6.dist-info/RECORD
