Metadata-Version: 2.4
Name: pixtreme-legacy
Version: 0.8.6
Summary: Legacy compatibility functions for pixtreme (_cp functions)
Project-URL: repository, https://github.com/sync-dev-org/pixtreme
Project-URL: issues, https://github.com/sync-dev-org/pixtreme/issues
Author-email: minamik <mia@sync.dev>
License-Expression: MIT
License-File: LICENSE
Classifier: Development Status :: 7 - Inactive
Classifier: Environment :: GPU :: NVIDIA CUDA :: 12
Classifier: Intended Audience :: Developers
Classifier: License :: OSI Approved :: MIT License
Classifier: Operating System :: Microsoft :: Windows
Classifier: Operating System :: POSIX :: Linux
Classifier: Programming Language :: Python :: 3.12
Classifier: Programming Language :: Python :: 3.13
Classifier: Topic :: Multimedia :: Graphics
Requires-Python: >=3.12
Requires-Dist: pixtreme>=0.7.3
